flash/__about__.py
flash/__init__.py
flash/__main__.py
flash/assets/example.wav
flash/assets/fish.jpg
flash/assets/road.png
flash/assets/starry_night.jpg
flash/audio/__init__.py
flash/audio/classification/__init__.py
flash/audio/classification/cli.py
flash/audio/classification/data.py
flash/audio/classification/input.py
flash/audio/classification/input_transform.py
flash/audio/speech_recognition/__init__.py
flash/audio/speech_recognition/backbone.py
flash/audio/speech_recognition/cli.py
flash/audio/speech_recognition/collate.py
flash/audio/speech_recognition/data.py
flash/audio/speech_recognition/input.py
flash/audio/speech_recognition/model.py
flash/audio/speech_recognition/output_transform.py
flash/core/__init__.py
flash/core/adapter.py
flash/core/classification.py
flash/core/finetuning.py
flash/core/heads.py
flash/core/hooks.py
flash/core/model.py
flash/core/registry.py
flash/core/regression.py
flash/core/trainer.py
flash/core/data/__init__.py
flash/core/data/base_viz.py
flash/core/data/batch.py
flash/core/data/callback.py
flash/core/data/data_module.py
flash/core/data/output.py
flash/core/data/properties.py
flash/core/data/splits.py
flash/core/data/transforms.py
flash/core/data/utils.py
flash/core/data/io/__init__.py
flash/core/data/io/classification_input.py
flash/core/data/io/input.py
flash/core/data/io/input_transform.py
flash/core/data/io/output.py
flash/core/data/io/output_transform.py
flash/core/data/io/transform_predictions.py
flash/core/data/utilities/__init__.py
flash/core/data/utilities/classification.py
flash/core/data/utilities/collate.py
flash/core/data/utilities/data_frame.py
flash/core/data/utilities/loading.py
flash/core/data/utilities/paths.py
flash/core/data/utilities/samples.py
flash/core/data/utilities/sort.py
flash/core/integrations/__init__.py
flash/core/integrations/fiftyone/__init__.py
flash/core/integrations/fiftyone/utils.py
flash/core/integrations/icevision/__init__.py
flash/core/integrations/icevision/adapter.py
lightning_flash-0.8.2.dist-info/LICENSE
lightning_flash-0.8.2.dist-info/METADATA
lightning_flash-0.8.2.dist-info/WHEEL
lightning_flash-0.8.2.dist-info/entry_points.txt
lightning_flash-0.8.2.dist-info/top_level.txt
lightning_flash-0.8.2.dist-info/RECORD
