Metadata-Version: 2.1
Name: lightning-flash
Version: 0.8.2
Summary: Your PyTorch AI Factory - Flash enables you to easily configure and run complex AI recipes.
Home-page: https://github.com/Lightning-AI/lightning-flash
Download-URL: https://github.com/Lightning-AI/lightning-flash
Author: PyTorchLightning et al.
Author-email: name@pytorchlightning.ai
License: Apache-2.0
Project-URL: Bug Tracker, https://github.com/Lightning-AI/lightning-flash/issues
Project-URL: Documentation, https://lightning-flash.rtfd.io/en/latest/
Project-URL: Source Code, https://github.com/Lightning-AI/lightning-flash
Keywords: deep learning,pytorch,AI
Classifier: Environment :: Console
Classifier: Natural Language :: English
Classifier: Development Status :: 4 - Beta
Classifier: Intended Audience :: Developers
Classifier: Topic :: Scientific/Engineering :: Artificial Intelligence
Classifier: Topic :: Scientific/Engineering :: Image Recognition
Classifier: Topic :: Scientific/Engineering :: Information Analysis
Classifier: Operating System :: OS Independent
Classifier: Programming Language :: Python :: 3
Classifier: Programming Language :: Python :: 3.8
Classifier: Programming Language :: Python :: 3.9
Classifier: Programming Language :: Python :: 3.10
Requires-Python: >=3.8
License-File: LICENSE
Requires-Dist: packaging
Requires-Dist: setuptools
Requires-Dist: numpy
Requires-Dist: torch (>1.7.0)
Requires-Dist: torchmetrics (<0.11.0,>0.7.0)
Requires-Dist: pytorch-lightning (<2.0.0,>1.8.0)
Requires-Dist: pyDeprecate (>0.2.0)
Requires-Dist: pandas (>1.1.0)
Requires-Dist: jsonargparse[signatures] (>=4.22.0)
Requires-Dist: click (>=7.1.2)
Requires-Dist: protobuf
Requires-Dist: fsspec[http] (>=2022.5.0)
Requires-Dist: lightning-utilities (>=0.4.1)
Provides-Extra: all
Requires-Dist: regex ; extra == 'all'
Requires-Dist: albumentations (>1.0.0) ; extra == 'all'
Requires-Dist: datasets (>=2.0.0) ; extra == 'all'
Requires-Dist: timm (>0.4.5) ; extra == 'all'
Requires-Dist: torchmetrics[text] (>0.5.0) ; extra == 'all'
Requires-Dist: sentence-transformers ; extra == 'all'
Requires-Dist: numpy (<1.24) ; extra == 'all'
Requires-Dist: torchvision ; extra == 'all'
Requires-Dist: pytorch-tabular (>=1.0.2) ; extra == 'all'
Requires-Dist: sentencepiece (>=0.1.95) ; extra == 'all'
Requires-Dist: scikit-learn ; extra == 'all'
Requires-Dist: ftfy (>6.0.0) ; extra == 'all'
Requires-Dist: torchaudio ; extra == 'all'
Requires-Dist: pytorch-forecasting (>=0.10.0) ; extra == 'all'
Requires-Dist: pytorchvideo (==0.1.2) ; extra == 'all'
Requires-Dist: pystiche (>1.0.0) ; extra == 'all'
Requires-Dist: icedata (>0.5.0) ; extra == 'all'
Requires-Dist: fiftyone ; extra == 'all'
Requires-Dist: filelock ; extra == 'all'
Requires-Dist: torchmetrics (>=0.10.0) ; extra == 'all'
Requires-Dist: icevision (>0.8) ; extra == 'all'
Requires-Dist: lightning-bolts (>=0.7.0) ; extra == 'all'
Requires-Dist: transformers (>=4.13.0) ; extra == 'all'
Requires-Dist: ftfy ; extra == 'all'
Requires-Dist: kornia (>=0.5.1) ; extra == 'all'
Requires-Dist: omegaconf ; extra == 'all'
Requires-Dist: sahi (<0.11,>=0.8.19) ; extra == 'all'
Requires-Dist: librosa (>=0.8.1post2) ; extra == 'all'
Requires-Dist: datasets (>1.16.1) ; extra == 'all'
Requires-Dist: Pillow (>7.1) ; extra == 'all'
Requires-Dist: Pillow (>8.0) ; extra == 'all'
Provides-Extra: audio
Requires-Dist: librosa (>=0.8.1post2) ; extra == 'audio'
Requires-Dist: datasets (>1.16.1) ; extra == 'audio'
Requires-Dist: torchaudio ; extra == 'audio'
Requires-Dist: numpy (<1.24) ; extra == 'audio'
Requires-Dist: torchvision ; extra == 'audio'
Requires-Dist: transformers (>=4.13.0) ; extra == 'audio'
Provides-Extra: base
Requires-Dist: protobuf ; extra == 'base'
Requires-Dist: click (>=7.1.2) ; extra == 'base'
Requires-Dist: jsonargparse[signatures] (>=4.22.0) ; extra == 'base'
Requires-Dist: setuptools ; extra == 'base'
Requires-Dist: lightning-utilities (>=0.4.1) ; extra == 'base'
Requires-Dist: pyDeprecate (>0.2.0) ; extra == 'base'
Requires-Dist: fsspec[http] (>=2022.5.0) ; extra == 'base'
Requires-Dist: pytorch-lightning (<2.0.0,>1.8.0) ; extra == 'base'
Requires-Dist: pandas (>1.1.0) ; extra == 'base'
Requires-Dist: packaging ; extra == 'base'
Requires-Dist: torch (>1.7.0) ; extra == 'base'
Requires-Dist: torchmetrics (<0.11.0,>0.7.0) ; extra == 'base'
Requires-Dist: numpy ; extra == 'base'
Provides-Extra: core
Requires-Dist: regex ; extra == 'core'
Requires-Dist: albumentations (>1.0.0) ; extra == 'core'
Requires-Dist: datasets (>=2.0.0) ; extra == 'core'
Requires-Dist: timm (>0.4.5) ; extra == 'core'
Requires-Dist: torchmetrics[text] (>0.5.0) ; extra == 'core'
Requires-Dist: sentence-transformers ; extra == 'core'
Requires-Dist: torchvision ; extra == 'core'
Requires-Dist: pytorch-tabular (>=1.0.2) ; extra == 'core'
Requires-Dist: sentencepiece (>=0.1.95) ; extra == 'core'
Requires-Dist: scikit-learn ; extra == 'core'
Requires-Dist: ftfy (>6.0.0) ; extra == 'core'
Requires-Dist: pytorch-forecasting (>=0.10.0) ; extra == 'core'
Requires-Dist: pystiche (>1.0.0) ; extra == 'core'
Requires-Dist: icedata (>0.5.0) ; extra == 'core'
Requires-Dist: filelock ; extra == 'core'
Requires-Dist: torchmetrics (>=0.10.0) ; extra == 'core'
Requires-Dist: icevision (>0.8) ; extra == 'core'
Requires-Dist: lightning-bolts (>=0.7.0) ; extra == 'core'
Requires-Dist: transformers (>=4.13.0) ; extra == 'core'
Requires-Dist: ftfy ; extra == 'core'
Requires-Dist: omegaconf ; extra == 'core'
Requires-Dist: sahi (<0.11,>=0.8.19) ; extra == 'core'
Requires-Dist: Pillow (>8.0) ; extra == 'core'
Provides-Extra: dev
Requires-Dist: pytest-doctestplus (==0.13.0) ; extra == 'dev'
Requires-Dist: regex ; extra == 'dev'
Requires-Dist: albumentations (>1.0.0) ; extra == 'dev'
Requires-Dist: datasets (>=2.0.0) ; extra == 'dev'
Requires-Dist: pytest-rerunfailures (==11.1.2) ; extra == 'dev'
Requires-Dist: sphinx-autodoc-typehints (>=1.0) ; extra == 'dev'
Requires-Dist: timm (>0.4.5) ; extra == 'dev'
Requires-Dist: pytest-forked (==1.6.0) ; extra == 'dev'
Requires-Dist: torchmetrics[text] (>0.5.0) ; extra == 'dev'
Requires-Dist: sentence-transformers ; extra == 'dev'
Requires-Dist: numpy (<1.24) ; extra == 'dev'
Requires-Dist: torchvision ; extra == 'dev'
Requires-Dist: pytest (==7.4.0) ; extra == 'dev'
Requires-Dist: sphinx (>=4.0) ; extra == 'dev'
Requires-Dist: pandoc (>=1.0) ; extra == 'dev'
Requires-Dist: nbformat ; extra == 'dev'
Requires-Dist: pytorch-tabular (>=1.0.2) ; extra == 'dev'
Requires-Dist: sentencepiece (>=0.1.95) ; extra == 'dev'
Requires-Dist: pytest-mock (==3.11.1) ; extra == 'dev'
Requires-Dist: myst-parser (>=0.15) ; extra == 'dev'
Requires-Dist: scikit-learn ; extra == 'dev'
Requires-Dist: ipython[notebook] ; extra == 'dev'
Requires-Dist: ftfy (>6.0.0) ; extra == 'dev'
Requires-Dist: nbsphinx (>=0.8.5) ; extra == 'dev'
Requires-Dist: torchaudio ; extra == 'dev'
Requires-Dist: pytorch-forecasting (>=0.10.0) ; extra == 'dev'
Requires-Dist: pytorchvideo (==0.1.2) ; extra == 'dev'
Requires-Dist: pystiche (>1.0.0) ; extra == 'dev'
Requires-Dist: icedata (>0.5.0) ; extra == 'dev'
Requires-Dist: sphinx-togglebutton (>=0.2) ; extra == 'dev'
Requires-Dist: jinja2 (>=3.0.0) ; extra == 'dev'
Requires-Dist: fiftyone ; extra == 'dev'
Requires-Dist: sphinx-copybutton (>=0.3) ; extra == 'dev'
Requires-Dist: filelock ; extra == 'dev'
Requires-Dist: sphinxcontrib-fulltoc (>=1.0) ; extra == 'dev'
Requires-Dist: sphinxcontrib-mockautodoc ; extra == 'dev'
Requires-Dist: torchmetrics (>=0.10.0) ; extra == 'dev'
Requires-Dist: icevision (>0.8) ; extra == 'dev'
Requires-Dist: lightning-bolts (>=0.7.0) ; extra == 'dev'
Requires-Dist: transformers (>=4.13.0) ; extra == 'dev'
Requires-Dist: ftfy ; extra == 'dev'
Requires-Dist: kornia (>=0.5.1) ; extra == 'dev'
Requires-Dist: omegaconf ; extra == 'dev'
Requires-Dist: docutils (>=0.16) ; extra == 'dev'
Requires-Dist: sahi (<0.11,>=0.8.19) ; extra == 'dev'
Requires-Dist: librosa (>=0.8.1post2) ; extra == 'dev'
Requires-Dist: datasets (>1.16.1) ; extra == 'dev'
Requires-Dist: coverage[toml] ; extra == 'dev'
Requires-Dist: Pillow (>7.1) ; extra == 'dev'
Requires-Dist: Pillow (>8.0) ; extra == 'dev'
Requires-Dist: sphinx-paramlinks (>=0.5.1) ; extra == 'dev'
Provides-Extra: docs
Requires-Dist: pandoc (>=1.0) ; extra == 'docs'
Requires-Dist: docutils (>=0.16) ; extra == 'docs'
Requires-Dist: sphinx-autodoc-typehints (>=1.0) ; extra == 'docs'
Requires-Dist: myst-parser (>=0.15) ; extra == 'docs'
Requires-Dist: sphinx-copybutton (>=0.3) ; extra == 'docs'
Requires-Dist: ipython[notebook] ; extra == 'docs'
Requires-Dist: nbsphinx (>=0.8.5) ; extra == 'docs'
Requires-Dist: sphinx-paramlinks (>=0.5.1) ; extra == 'docs'
Requires-Dist: sphinxcontrib-fulltoc (>=1.0) ; extra == 'docs'
Requires-Dist: sphinxcontrib-mockautodoc ; extra == 'docs'
Requires-Dist: sphinx (>=4.0) ; extra == 'docs'
Requires-Dist: sphinx-togglebutton (>=0.2) ; extra == 'docs'
Requires-Dist: jinja2 (>=3.0.0) ; extra == 'docs'
Requires-Dist: nbformat ; extra == 'docs'
Provides-Extra: graph
Requires-Dist: class-resolver (>=0.3.2) ; extra == 'graph'
Requires-Dist: torch-sparse ; extra == 'graph'
Requires-Dist: networkx ; extra == 'graph'
Requires-Dist: torch-geometric (>=2.0.0) ; extra == 'graph'
Requires-Dist: torchvision (==0.14.1) ; extra == 'graph'
Requires-Dist: torch-scatter ; extra == 'graph'
Requires-Dist: torch-cluster ; extra == 'graph'
Requires-Dist: torch (==1.13.1) ; extra == 'graph'
Provides-Extra: image
Requires-Dist: icedata (>0.5.0) ; extra == 'image'
Requires-Dist: regex ; extra == 'image'
Requires-Dist: albumentations (>1.0.0) ; extra == 'image'
Requires-Dist: sahi (<0.11,>=0.8.19) ; extra == 'image'
Requires-Dist: ftfy (>6.0.0) ; extra == 'image'
Requires-Dist: timm (>0.4.5) ; extra == 'image'
Requires-Dist: pystiche (>1.0.0) ; extra == 'image'
Requires-Dist: Pillow (>8.0) ; extra == 'image'
Requires-Dist: torchvision ; extra == 'image'
Requires-Dist: icevision (>0.8) ; extra == 'image'
Requires-Dist: lightning-bolts (>=0.7.0) ; extra == 'image'
Provides-Extra: image_baal
Requires-Dist: baal (>=1.3.2) ; extra == 'image_baal'
Provides-Extra: image_extras
Requires-Dist: torch ; extra == 'image_extras'
Requires-Dist: fiftyone ; extra == 'image_extras'
Requires-Dist: fairscale ; extra == 'image_extras'
Requires-Dist: effdet ; extra == 'image_extras'
Requires-Dist: fastface ; extra == 'image_extras'
Requires-Dist: kornia (>0.5.1) ; extra == 'image_extras'
Requires-Dist: classy-vision ; extra == 'image_extras'
Requires-Dist: matplotlib (>3.0.0) ; extra == 'image_extras'
Requires-Dist: torchmetrics ; extra == 'image_extras'
Requires-Dist: learn2learn ; (platform_system != "Windows") and extra == 'image_extras'
Provides-Extra: image_segm
Requires-Dist: segmentation-models-pytorch (>0.2.0) ; extra == 'image_segm'
Provides-Extra: image_vissl
Requires-Dist: torchvision (>0.11.0) ; extra == 'image_vissl'
Requires-Dist: icevision (>0.11) ; extra == 'image_vissl'
Requires-Dist: vissl (>=0.1.5) ; extra == 'image_vissl'
Requires-Dist: sahi (>0.10.0) ; extra == 'image_vissl'
Requires-Dist: torch (>1.10.0) ; extra == 'image_vissl'
Requires-Dist: torchmetrics (>0.10.0) ; extra == 'image_vissl'
Requires-Dist: timm (>0.9.0) ; extra == 'image_vissl'
Provides-Extra: pointcloud
Requires-Dist: tensorboard ; extra == 'pointcloud'
Requires-Dist: open3d (>=0.17.0) ; extra == 'pointcloud'
Provides-Extra: serve
Requires-Dist: cytoolz (>0.11) ; extra == 'serve'
Requires-Dist: torchvision (>0.10.0) ; extra == 'serve'
Requires-Dist: tqdm (>4.60) ; extra == 'serve'
Requires-Dist: fastapi (>0.65) ; extra == 'serve'
Requires-Dist: aiofiles (>22.1.0) ; extra == 'serve'
Requires-Dist: uvicorn[standard] (>=0.12.0) ; extra == 'serve'
Requires-Dist: pyyaml (>5.4) ; extra == 'serve'
Requires-Dist: pillow (>9.0.0) ; extra == 'serve'
Requires-Dist: starlette ; extra == 'serve'
Requires-Dist: jinja2 (>=3.0.0) ; extra == 'serve'
Requires-Dist: graphviz (>=0.19) ; extra == 'serve'
Requires-Dist: pydantic (>1.8.1) ; extra == 'serve'
Provides-Extra: tabular
Requires-Dist: omegaconf ; extra == 'tabular'
Requires-Dist: pytorch-tabular (>=1.0.2) ; extra == 'tabular'
Requires-Dist: scikit-learn ; extra == 'tabular'
Requires-Dist: pytorch-forecasting (>=0.10.0) ; extra == 'tabular'
Requires-Dist: torchmetrics (>=0.10.0) ; extra == 'tabular'
Provides-Extra: test
Requires-Dist: pytest-doctestplus (==0.13.0) ; extra == 'test'
Requires-Dist: pytest-rerunfailures (==11.1.2) ; extra == 'test'
Requires-Dist: pytest-mock (==3.11.1) ; extra == 'test'
Requires-Dist: coverage[toml] ; extra == 'test'
Requires-Dist: pytest-forked (==1.6.0) ; extra == 'test'
Requires-Dist: pytest (==7.4.0) ; extra == 'test'
Provides-Extra: text
Requires-Dist: regex ; extra == 'text'
Requires-Dist: sentencepiece (>=0.1.95) ; extra == 'text'
Requires-Dist: datasets (>=2.0.0) ; extra == 'text'
Requires-Dist: filelock ; extra == 'text'
Requires-Dist: torchmetrics[text] (>0.5.0) ; extra == 'text'
Requires-Dist: sentence-transformers ; extra == 'text'
Requires-Dist: ftfy ; extra == 'text'
Requires-Dist: torchvision ; extra == 'text'
Requires-Dist: transformers (>=4.13.0) ; extra == 'text'
Provides-Extra: video
Requires-Dist: kornia (>=0.5.1) ; extra == 'video'
Requires-Dist: fiftyone ; extra == 'video'
Requires-Dist: pytorchvideo (==0.1.2) ; extra == 'video'
Requires-Dist: Pillow (>7.1) ; extra == 'video'
Requires-Dist: torchvision ; extra == 'video'
Provides-Extra: vision
Requires-Dist: icedata (>0.5.0) ; extra == 'vision'
Requires-Dist: kornia (>=0.5.1) ; extra == 'vision'
Requires-Dist: regex ; extra == 'vision'
Requires-Dist: albumentations (>1.0.0) ; extra == 'vision'
Requires-Dist: sahi (<0.11,>=0.8.19) ; extra == 'vision'
Requires-Dist: fiftyone ; extra == 'vision'
Requires-Dist: ftfy (>6.0.0) ; extra == 'vision'
Requires-Dist: timm (>0.4.5) ; extra == 'vision'
Requires-Dist: Pillow (>7.1) ; extra == 'vision'
Requires-Dist: pystiche (>1.0.0) ; extra == 'vision'
Requires-Dist: Pillow (>8.0) ; extra == 'vision'
Requires-Dist: torchvision ; extra == 'vision'
Requires-Dist: pytorchvideo (==0.1.2) ; extra == 'vision'
Requires-Dist: icevision (>0.8) ; extra == 'vision'
Requires-Dist: lightning-bolts (>=0.7.0) ; extra == 'vision'
